fsm-assignments/problem1_seqdet/seq_detect_mealy.v
module seq_detect_mealy(
    input  wire clk,
    input  wire rst,   // synchronous, active-high
    input  wire din,   // serial input bit per clock
    output wire y      // 1-cycle pulse when 1101 seen
);

    // State encoding
    parameter S0   = 2'b00,  // no match
              S1   = 2'b01,  // seen '1'
              S11  = 2'b10,  // seen '11'
              S110 = 2'b11;  // seen '110'

    reg [1:0] state_present, state_next;

    // State register
    always @(posedge clk) begin
        if (rst)
            state_present <= S0;
        else
            state_present <= state_next;
    end

    // Mealy output: detect when in S110 and din=1
    assign y = (state_present == S110) && (din == 1'b1);

    // Next-state logic
    always @(*) begin
        state_next = state_present; // default
        case (state_present)
            S0:   state_next = din ? S1   : S0;
            S1:   state_next = din ? S11  : S0;
            S11:  state_next = din ? S11  : S110;
            S110: state_next = din ? S11  : S0; // overlap 
            default: state_next = S0;
        endcase
    end
endmodule

fsm-assignments/problem1_seqdet/tb_seq_detect_mealy.v
`timescale 1ns/1ps

module tb_seq_detect_mealy;
    reg clk, rst, din;
    wire y;

    // DUT 
    seq_detect_mealy dut (
        .clk(clk),
        .rst(rst),
        .din(din),
        .y(y)
    );

    // Clock generation: 100 MHz -> 10 ns period
    initial begin
        clk = 0;
        forever #5 clk = ~clk; // toggle 5ns
    end

    // bitstream with overlaps: 11011011101
    reg [10:0] bitstream = 11'b11011011101;
    integer i;

    initial begin
        $dumpfile("dump.vcd");
        $dumpvars(0, tb_seq_detect_mealy);

        // Initialize
        rst = 1;
        din = 0;

        // Apply reset for a couple of cycles
        repeat(2) @(posedge clk);
        rst = 0;

        // Send bits MSB -> LSB, one per clock
        for (i = 10; i >= 0; i = i - 1) begin
            @(posedge clk);
            din = bitstream[i];
        end

        // extra idle clocks
        repeat(3) @(posedge clk);
        $finish;
    end

    // Log time, din, y
    initial begin
        $display("Time\tclk\trst\tdin\ty");
        $monitor("%0dns\t%b\t%b\t%b\t%b", $time, clk, rst, din, y);
    end

endmodule

fsm-assignments/problem1_seqdet/waves/dump.vcd
$date
	Sun Aug 17 23:56:05 2025
$end
$version
	Icarus Verilog
$end
$timescale
	1ps
$end
$scope module tb_seq_detect_mealy $end
$var wire 1 ! y $end
$var reg 11 " bitstream [10:0] $end
$var reg 1 # clk $end
$var reg 1 $ din $end
$var reg 1 % rst $end
$var integer 32 & i [31:0] $end
$scope module dut $end
$var wire 1 # clk $end
$var wire 1 $ din $end
$var wire 1 % rst $end
$var wire 1 ! y $end
$var reg 2 ' state_next [1:0] $end
$var reg 2 ( state_present [1:0] $end
$upscope $end
$upscope $end
$enddefinitions $end
#0
$dumpvars
bx (
b0 '
bx &
1%
0$
0#
b11011011101 "
0!
$end
#5000
b0 (
1#
#10000
0#
#15000
b1010 &
0%
1#
#20000
0#
#25000
b1 '
b1001 &
1$
1#
#30000
0#
#35000
b10 '
b1 (
b1000 &
1#
#40000
0#
#45000
b10 (
b11 '
b111 &
0$
1#
#50000
0#
#55000
1!
b11 (
b10 '
b110 &
1$
1#
#60000
0#
#65000
0!
b10 (
b101 &
1#
#70000
0#
#75000
b11 '
b100 &
0$
1#
#80000
0#
#85000
1!
b11 (
b10 '
b11 &
1$
1#
#90000
0#
#95000
0!
b10 (
b10 &
1#
#100000
0#
#105000
b1 &
1#
#110000
0#
#115000
b11 '
b0 &
0$
1#
#120000
0#
#125000
1!
b11 (
b10 '
b11111111111111111111111111111111 &
1$
1#
#130000
0#
#135000
0!
b10 (
1#
